tdd/__init__.py
tdd/common.py
tdd/config.py
tdd/context.py
tdd/errors.py
tdd/metadata.py
tdd/paths.py
tdd/registration.py
tdd/sparql.py
tdd/td.py
tdd/utils.py
tdd/data/fixed-ctx.json
tdd/data/fixed-discovery-ctx.json
tdd/data/td-json-schema-validation.json
tdd/data/td-validation.ttl
tdd/data/td.ttl
tdd/data/tdd-description.json
tdd/lib/_213a.js
tdd/lib/frame-jsonld.js
tdd/lib/node_modules_node-fetch_src_utils_multipart-parser_js.js
tdd/lib/transform-to-nt.js
tdd/lib/vendors-node_modules_ky-universal_index_js.js
tdd/lib/vendors-node_modules_ky_distribution_index_js.js
tdd/tests/__init__.py
tdd/tests/conftest.py
tdd/tests/test_discovery.py
tdd/tests/test_modify.py
tdd/tests/test_registration.py
tdd/tests/test_routes.py
tdd/tests/data/17_things.nquads
tdd/tests/data/bad-json-schema.td.jsonld
tdd/tests/data/bad-json.td.jsonld
tdd/tests/data/registration-data.ttl
tdd/tests/data/smart-coffee-machine.n3
tdd/tests/data/smart-coffee-machine.td.jsonld
tdd/tests/data/smart-coffee-machine.ttl
tdd/tests/data/smart-coffee-machine.xml
tdd/tests/data/smart-coffee-machine_shacl_nok.ttl
tdd/tests/data/smart-coffee-machine_shacl_ok.ttl
tdd/tests/data/smart_coffe_machine_expired.nquads
tdd/tests/data/smart_coffe_machine_init.nquads
tdd/tests/data/tdd-description.json
tdd/tests/data/td/17_TD_RAW/actions-events-thing.td.jsonld
tdd/tests/data/td/17_TD_RAW/air-quality-sensor.td.jsonld
tdd/tests/data/td/17_TD_RAW/alarm.td.jsonld
tdd/tests/data/td/17_TD_RAW/barmometric-pressure-sensor.td.jsonld
tdd/tests/data/td/17_TD_RAW/binary-sensor.td.jsonld
tdd/tests/data/td/17_TD_RAW/camera.td.jsonld
tdd/tests/data/td/17_TD_RAW/color-control.td.jsonld
tdd/tests/data/td/17_TD_RAW/color-sensor.td.jsonld
tdd/tests/data/td/17_TD_RAW/dimmable-color-light.td.jsonld
tdd/tests/data/td/17_TD_RAW/dimmable-light.td.jsonld
tdd/tests/data/td/17_TD_RAW/tum-daylight.td.jsonld
tdd/tests/data/td/17_TD_RAW/tum-dimmer-switch.td.jsonld
tdd/tests/data/td/17_TD_RAW/tum-hue-indoor-sensor1.td.jsonld
domus_tdd_api-1.0.2.dist-info/LICENSE.md
domus_tdd_api-1.0.2.dist-info/METADATA
domus_tdd_api-1.0.2.dist-info/WHEEL
domus_tdd_api-1.0.2.dist-info/entry_points.txt
domus_tdd_api-1.0.2.dist-info/top_level.txt
domus_tdd_api-1.0.2.dist-info/RECORD
