Metadata-Version: 2.1
Name: domus-tdd-api
Version: 1.0.2
Summary: A modular and semantic Thing Description Directory
Home-page: https://github.com/eclipse-thingweb/domus-tdd-api
Author: Eclipse Thingweb Project
Maintainer: Eclipse Thingweb Project
Project-URL: Releases, https://github.com/eclipse-thingweb/domus-tdd-api/tags
Project-URL: Source, https://github.com/eclipse-thingweb/domus-tdd-api
Keywords: web of things,thing description directory,wot,tdd
Classifier: Programming Language :: Python
Classifier: Framework :: Flask
License-File: LICENSE.md
Requires-Dist: Flask
Requires-Dist: httpx
Requires-Dist: jsonschema
Requires-Dist: rdflib
Requires-Dist: json-merge-patch
Requires-Dist: python-configuration[toml]
Requires-Dist: pyshacl
Requires-Dist: importlib-metadata
Requires-Dist: toml
Provides-Extra: dev
Requires-Dist: pytest ; extra == 'dev'
Requires-Dist: pytest-env ; extra == 'dev'
Requires-Dist: pytest-httpx ; extra == 'dev'
Requires-Dist: jsoncomparison ; extra == 'dev'
Requires-Dist: pytz ; extra == 'dev'
Requires-Dist: black ; extra == 'dev'
Requires-Dist: flake8 ; extra == 'dev'
Requires-Dist: requests ; extra == 'dev'
Provides-Extra: prod
Requires-Dist: gunicorn ; extra == 'prod'
